rpe2_code/__init__.py
rpe2_code/recruit_plot_easy_2_database.py
rpe2_code/recruit_plot_easy_2_describe.py
rpe2_code/recruit_plot_easy_2_plot.py
rpe2_code/rpe2_main.py
rpe2_code/supports/__init__.py
rpe2_code/supports/agnostic_reader.py
rpe2_code/supports/bam_parser.py
rpe2_code/supports/blast_parser.py
rpe2_code/supports/cig_parser.py
rpe2_code/supports/fasta_reader.py
rpe2_code/supports/file_checker.py
rpe2_code/supports/mdz_parser.py
rpe2_code/supports/protein_predictor.py
rpe2_code/supports/sam_parser.py
RecruitPlotEasy-3.2.3.dist-info/METADATA
RecruitPlotEasy-3.2.3.dist-info/WHEEL
RecruitPlotEasy-3.2.3.dist-info/entry_points.txt
RecruitPlotEasy-3.2.3.dist-info/top_level.txt
RecruitPlotEasy-3.2.3.dist-info/RECORD
