Metadata-Version: 2.1
Name: RecruitPlotEasy
Version: 3.2.3
Summary: A tool for visualizing short read mapping efforts
Author: Kenji Gerhardt
Author-email: kenji.gerhardt@gmail.com
Requires-Python: >=3.9
Requires-Dist: numpy
Requires-Dist: pyrodigal (>=2.0)
Requires-Dist: plotly
